spotify_grab_current_playlists/cred.py
spotify_grab_current_playlists/cred_my.py
spotify_grab_current_playlists/spotify_grab_current_playlists.py
spotify_playlist_exporter-0.0.3.dist-info/LICENSE.txt
spotify_playlist_exporter-0.0.3.dist-info/METADATA
spotify_playlist_exporter-0.0.3.dist-info/WHEEL
spotify_playlist_exporter-0.0.3.dist-info/top_level.txt
spotify_playlist_exporter-0.0.3.dist-info/RECORD
