Metadata-Version: 2.1
Name: spotify-playlist-exporter
Version: 0.0.3
Summary: A small example package
Author-email: Example Author <bebissig@gmail.com>
Project-URL: Homepage, https://github.com/bebissig/spotify_grab_current_playlists
Classifier: Programming Language :: Python :: 3
Classifier: License :: OSI Approved :: MIT License
Classifier: Operating System :: OS Independent
Requires-Python: >=3.7
License-File: LICENSE.txt
Requires-Dist: async-timeout (==4.0.2)
Requires-Dist: certifi (==2023.5.7)
Requires-Dist: charset-normalizer (==3.1.0)
Requires-Dist: et-xmlfile (==1.1.0)
Requires-Dist: idna (==3.4)
Requires-Dist: importlib-metadata (==6.6.0)
Requires-Dist: numpy (==1.21.6)
Requires-Dist: openpyxl (==3.1.2)
Requires-Dist: pandas (==1.3.5)
Requires-Dist: python-dateutil (==2.8.2)
Requires-Dist: pytz (==2023.3)
Requires-Dist: redis (==4.5.5)
Requires-Dist: requests (==2.30.0)
Requires-Dist: six (==1.16.0)
Requires-Dist: spotipy (==2.23.0)
Requires-Dist: typing-extensions (==4.5.0)
Requires-Dist: urllib3 (==2.0.2)
Requires-Dist: zipp (==3.15.0)
